{
 "full_text": "Believe it or not, there was a time when searching the web for images was not possible. Twenty-five years ago, Google launched image search, and it's celebrating by looking back at its biggest visual milestones and refreshing the experience for today's searchers. The celebration also includes expanded AI because that's just how Google rolls in 2026. Google claims the impetus for image search a quarter-century ago was the green Versace dress Jennifer Lopez wore to the 2000 Grammy Awards. If you were alive at the time, you probably remember the one. Google engineers understood that people searching for the dress didn't want to read about it—they just wanted to see it. The company got to work building image search, launching the first version in July 2001. Twenty-five years later, it's easy to take for granted that you can search for Lopez's green dress or whatever else strikes your fancy. Currently, going to the Google image search site shows a plain search bar for finding images. It's a refreshingly minimalist interface for the modern web. Even Google's search homepage has a smattering of AI buttons and drop-down menus. That will change when the new Google Images rolls out. Read full article Comments",
 "item": {
  "category": "open",
  "extra": {},
  "full_text_available": true,
  "full_text_file": "articles/news/ce137642f5f56b6e.json",
  "id": "ce137642f5f56b6e",
  "kind": "news",
  "lang": "en",
  "published_at": "2026-07-14T16:28:14Z",
  "score": 0.5319,
  "section": "news",
  "source": "Ars Technica · AI",
  "source_id": "ars_ai",
  "summary": "The new Google image search will use your \"unique interests\" to create an always-updated gallery.",
  "tags": [],
  "title": "Google revamps image search for its 25th anniversary with more images and more AI",
  "url": "https://arstechnica.com/google/2026/07/google-revamps-image-search-for-its-25th-anniversary-with-more-images-and-more-ai/"
 },
 "meta": {
  "generated_at": "2026-07-15T03:30:33Z",
  "item_id": "ce137642f5f56b6e",
  "section": "news",
  "source": "Ars Technica · AI",
  "source_id": "ars_ai"
 }
}
